[
  {
    "description": "This is apartment 122.",
    "start_time": 4.880000000000001,
    "end_time": 10.44
  },
  {
    "description": "Try number 11 priority one top front crack.",
    "start_time": 19.28,
    "end_time": 24.54
  },
  {
    "description": "Track, tread number 10, priority one, top rear crack, screenshot.",
    "start_time": 24.54,
    "end_time": 37.3
  },
  {
    "description": "tread number 18 priority one bottom rear crack tread number 17 priority one",
    "start_time": 51.5,
    "end_time": 61.1
  },
  {
    "description": "bottom rear crack tread number 16 priority one bottom rear crack tread",
    "start_time": 61.1,
    "end_time": 65.56
  },
  {
    "description": "Tread number 15, priority one, bottom rear crack.",
    "start_time": 65.56,
    "end_time": 68.72
  },
  {
    "description": "Screenshot, try number 14, priority one, bottom rear crack.",
    "start_time": 69.5,
    "end_time": 74.1
  },
  {
    "description": "Tread number 13, priority one, bottom rear crack.",
    "start_time": 75.22,
    "end_time": 84.58
  },
  {
    "description": "Screenshot, tread number 12, priority one,",
    "start_time": 84.96,
    "end_time": 93.0
  },
  {
    "description": "bottom rear crack tread number 11 priority one bottom rear crack tread",
    "start_time": 93.0,
    "end_time": 99.1
  },
  {
    "description": "number 10 priority one bottom rear crack",
    "start_time": 99.1,
    "end_time": 101.0
  },
  {
    "description": "at apartment 112.",
    "start_time": 111.1,
    "end_time": 115.2
  },
  {
    "description": "12.",
    "start_time": 143.76,
    "end_time": 145.16
  },
  {
    "description": "One for a finish screenshot.",
    "start_time": 177.29999999999998,
    "end_time": 181.62
  },
  {
    "description": "10.",
    "start_time": 208.5,
    "end_time": 209.18
  },
  {
    "description": "Department 118, tread number 18.",
    "start_time": 209.2,
    "end_time": 213.9
  },
  {
    "description": "Priority one, bottom rear crack.",
    "start_time": 214.88,
    "end_time": 217.46
  },
  {
    "description": "Tread number 17, priority one, bottom rear crack.",
    "start_time": 218.2,
    "end_time": 220.66
  },
  {
    "description": "Tread number 16, priority two, bottom rear crack.",
    "start_time": 221.2,
    "end_time": 223.66
  },
  {
    "description": "Tread number 15, priority two, bottom rear crack.",
    "start_time": 224.22,
    "end_time": 226.68
  },
  {
    "description": "tread number nine priority one bottom rear crack tread number eight priority one",
    "start_time": 233.14000000000001,
    "end_time": 239.38
  },
  {
    "description": "bottom rear crack",
    "start_time": 239.38,
    "end_time": 240.16
  },
  {
    "description": "tread number one priority two rear cracks",
    "start_time": 245.36,
    "end_time": 250.54
  },
  {
    "description": "Tread number eight priority one top rear crack",
    "start_time": 264.1,
    "end_time": 277.52
  },
  {
    "description": "Track number 9 priority 2 top rear crack.",
    "start_time": 277.52,
    "end_time": 286.44
  },
  {
    "description": "Track number 18 priority 1 top rear crack.",
    "start_time": 294.8,
    "end_time": 299.38
  },
  {
    "description": "Now department 126, tread 18, priority 2, bottom rear crack, tread 17, priority 2, bottom rear crack.",
    "start_time": 301.3,
    "end_time": 311.68
  },
  {
    "description": "Tread 9, priority 1, bottom rear crack.",
    "start_time": 318.06,
    "end_time": 321.5
  },
  {
    "description": "I'm going to try to 8 priority 1 bottom rear crack, screenshot.",
    "start_time": 321.5,
    "end_time": 330.0
  },
  {
    "description": "Try number two priority one bottom rear crack.",
    "start_time": 339.02000000000004,
    "end_time": 360.38
  },
  {
    "description": "Dread number two priority two top center crack.",
    "start_time": 360.38,
    "end_time": 368.3
  },
  {
    "description": "apartment 137, building one, tread 16, priority one, top front and rear cracks, screenshot.",
    "start_time": 398.62,
    "end_time": 415.02
  },
  {
    "description": "Tread number eight, priority two, top front and rear cracks.",
    "start_time": 426.28000000000003,
    "end_time": 430.96
  },
  {
    "description": "Tread number five, priority two, top front and rear cracks.",
    "start_time": 433.12,
    "end_time": 436.7
  },
  {
    "description": "Tread number four, priority two, top front and rear cracks.",
    "start_time": 436.7,
    "end_time": 438.28
  },
  {
    "description": "tread 16, priority one, bottom rear crack.",
    "start_time": 445.02,
    "end_time": 451.62
  },
  {
    "description": "tread number eight, priority two, bottom rear crack.",
    "start_time": 459.24,
    "end_time": 462.03
  },
  {
    "description": "tread number seven, priority one, bottom rear crack.",
    "start_time": 462.03,
    "end_time": 467.06
  },
  {
    "description": "I got apartment 117.",
    "start_time": 479.06,
    "end_time": 481.9
  },
  {
    "description": "That thing was going to go any second.",
    "start_time": 486.24,
    "end_time": 493.74
  },
  {
    "description": "Tread number seven, priority one, bottom front and rear cracks.",
    "start_time": 509.08,
    "end_time": 516.94
  },
  {
    "description": "Try number one, priority two, top front and rear cracks.",
    "start_time": 533.4200000000001,
    "end_time": 546.16
  },
  {
    "description": "priority one, top front crack.",
    "start_time": 576.14,
    "end_time": 578.1
  },
  {
    "description": "Building two.",
    "start_time": 633.16,
    "end_time": 634.66
  },
  {
    "description": "apartment 218.",
    "start_time": 634.66,
    "end_time": 636.12
  },
  {
    "description": "Now, department 226.",
    "start_time": 686.1,
    "end_time": 688.64
  },
  {
    "description": "Try number eight.",
    "start_time": 696.24,
    "end_time": 697.4
  }
]